MANIFEST.in
README.rst
setup.py
Carapace.egg-info/PKG-INFO
Carapace.egg-info/SOURCES.txt
Carapace.egg-info/dependency_links.txt
Carapace.egg-info/not-zip-safe
Carapace.egg-info/requires.txt
Carapace.egg-info/top_level.txt
carapace/__init__.py
carapace/config.py
carapace/meta.py
carapace/app/__init__.py
carapace/app/cred.py
carapace/app/service.py
carapace/app/shell/__init__.py
carapace/app/shell/base.py
carapace/app/shell/echoshell.py
carapace/app/shell/pythonshell.py
carapace/app/shell/service.py
carapace/sdk/__init__.py
carapace/sdk/const.py
carapace/sdk/exceptions.py
carapace/sdk/interfaces.py
carapace/sdk/registry.py
carapace/sdk/scripts.py
carapace/util/__init__.py
carapace/util/dist.py
carapace/util/ssh.py
twisted/plugins/carapace.py
twisted/plugins/carapace.pyc
twisted/plugins/dropin.cache