Metadata-Version: 1.0
Name: Carapace
Version: 0.3-dev
Summary: Carapace Shell Server
Home-page: http://github.com/oubiwann/carapace
Author: Duncan McGreggor
Author-email: duncan@cogitat.io
License: MIT
Platform: UNKNOWN
